{"cameraMode":{"drawMode":0,"name":"Shaded","section":"Shading Mode"},"sceneLighting":true,"audioPlay":false,"sceneViewState":{"m_AlwaysRefresh":false,"showFog":true,"showSkybox":true,"showFlares":true,"showImageEffects":true,"showParticleSystems":true,"showVisualEffectGraphs":true,"m_FxEnabled":true},"in2DMode":false,"pivot":{"x":206.89842224121095,"y":284.9584045410156,"z":-308.3308410644531},"rotation":{"x":-0.05908640846610069,"y":0.1701529622077942,"z":-0.010221889242529869,"w":-0.9835911989212036},"size":14.937610626220704,"orthographic":false}